abcunit_backend/__init__.py
abcunit_backend/base_handler.py
abcunit_backend/database_handler.py
abcunit_backend/file_system_handler.py
abcunit_backend-1.3.0.dist-info/LICENSE
abcunit_backend-1.3.0.dist-info/METADATA
abcunit_backend-1.3.0.dist-info/WHEEL
abcunit_backend-1.3.0.dist-info/top_level.txt
abcunit_backend-1.3.0.dist-info/RECORD
