Metadata-Version: 2.1
Name: abcunit-backend
Version: 1.3.0
Summary: Backend solution for abcunit success / failure logs
Home-page: https://github.com/cedadev/abcunit-backend
Author: Jonathan Haigh
Author-email: jonathan.haigh@stfc.ac.uk
License: BSD 2-Clause License
Platform: UNKNOWN
Requires-Python: >=3.5.0
Requires-Dist: psycopg2 (>=2.8.0)
Provides-Extra: dev
Requires-Dist: psycopg2 (>=2.8.0) ; extra == 'dev'
Requires-Dist: pytest (>=5.4.3) ; extra == 'dev'
Provides-Extra: docs
Requires-Dist: sphinx ; extra == 'docs'
Requires-Dist: sphinx-rtd-theme ; extra == 'docs'
Requires-Dist: nbsphinx ; extra == 'docs'
Requires-Dist: pandoc ; extra == 'docs'
Requires-Dist: ipython ; extra == 'docs'
Requires-Dist: m2r2 ; extra == 'docs'
